inorbit_edge_executor/__init__.py
inorbit_edge_executor/behavior_tree.py
inorbit_edge_executor/datatypes.py
inorbit_edge_executor/db.py
inorbit_edge_executor/dummy_backend.py
inorbit_edge_executor/exceptions.py
inorbit_edge_executor/inorbit.py
inorbit_edge_executor/logger.py
inorbit_edge_executor/mission.py
inorbit_edge_executor/observable.py
inorbit_edge_executor/sqlite_backend.py
inorbit_edge_executor/worker.py
inorbit_edge_executor/worker_pool.py
inorbit_edge_executor-4.0.0.dist-info/licenses/LICENSE
inorbit_edge_executor-4.0.0.dist-info/METADATA
inorbit_edge_executor-4.0.0.dist-info/WHEEL
inorbit_edge_executor-4.0.0.dist-info/top_level.txt
inorbit_edge_executor-4.0.0.dist-info/RECORD
