Metadata-Version: 2.4
Name: inorbit_edge_executor
Version: 4.0.0
Summary: InOrbit Edge Missions Executor
Author-email: Mariano Cereda <mariano.cereda@inorbit.ai>, Hernan Badenes <herchu@inorbit.ai>, Miguel Garcia <mike@inorbit.ai>
License: MIT
Classifier: Programming Language :: Python :: 3
Classifier: License :: OSI Approved :: MIT License
Classifier: Operating System :: OS Independent
Requires-Python: <3.15,>=3.10
License-File: LICENSE
Requires-Dist: async-timeout~=4.0.3
Requires-Dist: httpx~=0.28.1
Requires-Dist: pydantic<3.0.0,>=2.0.0
Requires-Dist: typing-extensions<5.0.0,>=4.7.1
Requires-Dist: aiosql~=9.0
Requires-Dist: aiosqlite~=0.19.0
Provides-Extra: dev
Requires-Dist: pytest~=8.4.1; extra == "dev"
Requires-Dist: pytest-httpx~=0.35.0; extra == "dev"
Requires-Dist: pytest-asyncio~=1.1.0; extra == "dev"
Requires-Dist: black~=25.1.0; extra == "dev"
Requires-Dist: bump-my-version~=1.2.1; extra == "dev"
Provides-Extra: docs
Requires-Dist: sphinx; extra == "docs"
Requires-Dist: mkdocs; extra == "docs"
Dynamic: license-file
